SuijiGuochengJiangyiZhongkeyuanSunyingFei/README.md
SuijiGuochengJiangyiZhongkeyuanSunyingFei/__init__.py
SuijiGuochengJiangyiZhongkeyuanSunyingFei/__main__.py
SuijiGuochengJiangyiZhongkeyuanSunyingFei/file.pdf
SuijiGuochengJiangyiZhongkeyuanSunyingFei/index.html
suiji_guocheng_jiangyi_zhongkeyuan_sunying_fei-2024.3.2.0.dist-info/METADATA
suiji_guocheng_jiangyi_zhongkeyuan_sunying_fei-2024.3.2.0.dist-info/WHEEL
suiji_guocheng_jiangyi_zhongkeyuan_sunying_fei-2024.3.2.0.dist-info/entry_points.txt
suiji_guocheng_jiangyi_zhongkeyuan_sunying_fei-2024.3.2.0.dist-info/top_level.txt
suiji_guocheng_jiangyi_zhongkeyuan_sunying_fei-2024.3.2.0.dist-info/RECORD
